MANIFEST.in
NEWS.txt
README.rst
ez_setup.py
setup.cfg
setup.py
toolshed/__init__.py
toolshed/files.py
toolshed/fmt.py
toolshed/pool.py
toolshed.egg-info/PKG-INFO
toolshed.egg-info/SOURCES.txt
toolshed.egg-info/dependency_links.txt
toolshed.egg-info/entry_points.txt
toolshed.egg-info/not-zip-safe
toolshed.egg-info/top_level.txt