Metadata-Version: 1.1
Name: toolshed
Version: 0.4.5
Summary: Tools for data
Home-page: https://github.com/brentp/toolshed/
Author: Brent Pedersen
Author-email: bpederse@gmail.com
License: BSD (2-clause)
Keywords: bioinformatics
Platform: UNKNOWN
Classifier: Topic :: Scientific/Engineering
Classifier: Topic :: Scientific/Engineering :: Bio-Informatics
Classifier: Topic :: Text Processing
Classifier: Topic :: Utilities
Classifier: Programming Language :: Python :: 2
Classifier: Programming Language :: Python :: 3
